utils/__init__.py
utils/knot_utils.py
utils_pedro/__init__.py
utils_pedro/knot_utils.py
utils_knot-1.0.4.dist-info/METADATA
utils_knot-1.0.4.dist-info/WHEEL
utils_knot-1.0.4.dist-info/top_level.txt
utils_knot-1.0.4.dist-info/RECORD
